distfeat/__init__.py
distfeat/__main__.py
distfeat/distfeat.py
resources/phoible.tsv
resources/tresoldi.tsv
resources/distances/mielke2012.tsv
resources/models/phoible.tsv
resources/models/tresoldi.tsv
distfeat-0.2.dist-info/AUTHORS.md
distfeat-0.2.dist-info/LICENSE
distfeat-0.2.dist-info/METADATA
distfeat-0.2.dist-info/WHEEL
distfeat-0.2.dist-info/entry_points.txt
distfeat-0.2.dist-info/top_level.txt
distfeat-0.2.dist-info/RECORD
