Metadata-Version: 2.1
Name: distfeat
Version: 0.2
Summary: Library for manipulation of phonological distinctive features
Home-page: https://github.com/tresoldi/distfeat
Author: Tiago Tresoldi
Author-email: tresoldi@shh.mpg.de
License: MIT
Keywords: distinctive features,segmental features,phonology,phonetics
Platform: UNKNOWN
Classifier: License :: OSI Approved :: MIT License
Classifier: Operating System :: OS Independent
Classifier: Programming Language :: Python :: 3
Classifier: Topic :: Software Development :: Libraries
Requires-Dist: pyclts
Requires-Dist: tabulate
